walitool/__init__.py
walitool/crossover.py
walitool/de.py
walitool/fitness.py
walitool/generator.py
walitool/mutate.py
walitool/selection.py
walitool-0.1.0.dist-info/METADATA
walitool-0.1.0.dist-info/WHEEL
walitool-0.1.0.dist-info/top_level.txt
walitool-0.1.0.dist-info/RECORD
