Metadata-Version: 2.4
Name: walitool
Version: 0.1.0
Summary: A differential evolution optimization toolbox
Author-email: Wally Hao <1276672206@qq.com>
Project-URL: Homepage, https://github.com/waliwuao/walitool
Project-URL: Repository, https://github.com/waliwuao/walitool
Project-URL: Issues, https://github.com/waliwuao/walitool/issues
Classifier: Programming Language :: Python :: 3
Classifier: License :: OSI Approved :: MIT License
Classifier: Operating System :: OS Independent
Classifier: Intended Audience :: Developers
Classifier: Intended Audience :: Science/Research
Classifier: Topic :: Scientific/Engineering :: Mathematics
Classifier: Topic :: Software Development :: Libraries
Requires-Python: >=3.8
Requires-Dist: numpy>=1.21.0
Requires-Dist: numba>=0.55.0
Provides-Extra: dev
Requires-Dist: pytest>=7.0; extra == "dev"
Requires-Dist: flake8>=4.0; extra == "dev"
Requires-Dist: black>=22.0; extra == "dev"
Requires-Dist: mypy>=0.990; extra == "dev"
Provides-Extra: docs
Requires-Dist: sphinx>=5.0; extra == "docs"
Requires-Dist: sphinx-rtd-theme>=1.0; extra == "docs"
